e2f_connect/__init__.py
e2f_connect/client.py
e2f_connect/errors.py
e2f_connect/types.py
e2f_connect/api/__init__.py
e2f_connect/api/llm_evaluation_request_endpoints/__init__.py
e2f_connect/api/llm_evaluation_request_endpoints/project_controller_check_evaluation_status.py
e2f_connect/api/llm_evaluation_request_endpoints/project_controller_get_domains.py
e2f_connect/api/llm_evaluation_request_endpoints/project_controller_get_languages.py
e2f_connect/api/llm_evaluation_request_endpoints/project_controller_get_metrics.py
e2f_connect/api/llm_evaluation_request_endpoints/project_controller_submit_evaluation.py
e2f_connect/models/__init__.py
e2f_connect/models/evaluation_request_dto.py
e2f_connect/models/evaluation_request_dto_metrics.py
e2f_connect-0.1.dist-info/LICENCE.txt
e2f_connect-0.1.dist-info/METADATA
e2f_connect-0.1.dist-info/WHEEL
e2f_connect-0.1.dist-info/top_level.txt
e2f_connect-0.1.dist-info/RECORD
