Metadata-Version: 2.1
Name: e2f-connect
Version: 0.1
Summary: 
